{
  "annotations": {
    "list": [
      {
        "builtIn": 1,
        "datasource": "-- Grafana --",
        "enable": true,
        "hide": true,
        "iconColor": "rgba(0, 211, 255, 1)",
        "name": "Annotations & Alerts",
        "type": "dashboard"
      }
    ]
  },
  "description": "Dashboard exposes telemetry data from Assetto Corsa",
  "editable": true,
  "gnetId": null,
  "graphTooltip": 0,
  "links": [],
  "panels": [
    {
      "aliasColors": {},
      "bars": false,
      "dashLength": 10,
      "dashes": false,
      "datasource": null,
      "fieldConfig": {
        "defaults": {
          "color": {},
          "custom": {},
          "thresholds": {
            "mode": "absolute",
            "steps": []
          },
          "unit": "velocitykmh"
        },
        "overrides": []
      },
      "fill": 1,
      "fillGradient": 0,
      "gridPos": {
        "h": 9,
        "w": 12,
        "x": 0,
        "y": 0
      },
      "hiddenSeries": false,
      "id": 4,
      "legend": {
        "alignAsTable": true,
        "avg": true,
        "current": true,
        "hideEmpty": false,
        "max": true,
        "min": false,
        "rightSide": false,
        "show": true,
        "total": false,
        "values": true
      },
      "lines": true,
      "linewidth": 1,
      "maxDataPoints": 200,
      "nullPointMode": "null",
      "options": {
        "alertThreshold": true
      },
      "percentage": false,
      "pluginVersion": "7.4.3",
      "pointradius": 2,
      "points": false,
      "renderer": "flot",
      "seriesOverrides": [],
      "spaceLength": 10,
      "stack": false,
      "steppedLine": false,
      "targets": [
        {
          "groupBy": [
            {
              "params": [
                "$__interval"
              ],
              "type": "time"
            },
            {
              "params": [
                "null"
              ],
              "type": "fill"
            }
          ],
          "orderByTime": "ASC",
          "policy": "default",
          "query": "from(bucket:\"assetto-corsa-telemetry\")\n  |> range(start:-1m)\n  |> filter(fn:(r) =>\n    r._measurement == \"speed at current time\"\n  )\n  |> aggregateWindow(every: 1s, fn: mean)",
          "refId": "A",
          "resultFormat": "time_series",
          "select": [
            [
              {
                "params": [
                  "value"
                ],
                "type": "field"
              },
              {
                "params": [],
                "type": "mean"
              }
            ]
          ],
          "tags": []
        }
      ],
      "thresholds": [],
      "timeFrom": null,
      "timeRegions": [],
      "timeShift": null,
      "title": "Speed Dashboard",
      "tooltip": {
        "shared": true,
        "sort": 0,
        "value_type": "individual"
      },
      "type": "graph",
      "xaxis": {
        "buckets": null,
        "mode": "time",
        "name": null,
        "show": true,
        "values": []
      },
      "yaxes": [
        {
          "$$hashKey": "object:438",
          "format": "velocitykmh",
          "label": null,
          "logBase": 1,
          "max": null,
          "min": null,
          "show": true
        },
        {
          "$$hashKey": "object:439",
          "format": "short",
          "label": null,
          "logBase": 1,
          "max": null,
          "min": null,
          "show": true
        }
      ],
      "yaxis": {
        "align": false,
        "alignLevel": null
      }
    },
    {
      "aliasColors": {},
      "bars": false,
      "dashLength": 10,
      "dashes": false,
      "datasource": null,
      "fieldConfig": {
        "defaults": {
          "color": {},
          "custom": {},
          "displayName": "RPM",
          "thresholds": {
            "mode": "absolute",
            "steps": []
          },
          "unit": "rotrpm"
        },
        "overrides": []
      },
      "fill": 1,
      "fillGradient": 0,
      "gridPos": {
        "h": 9,
        "w": 12,
        "x": 12,
        "y": 0
      },
      "hiddenSeries": false,
      "id": 2,
      "interval": null,
      "legend": {
        "alignAsTable": true,
        "avg": true,
        "current": true,
        "max": true,
        "min": true,
        "rightSide": false,
        "show": true,
        "total": false,
        "values": true
      },
      "lines": true,
      "linewidth": 1,
      "maxDataPoints": 500,
      "nullPointMode": "null",
      "options": {
        "alertThreshold": true
      },
      "percentage": false,
      "pluginVersion": "7.4.3",
      "pointradius": 2,
      "points": false,
      "renderer": "flot",
      "seriesOverrides": [],
      "spaceLength": 10,
      "stack": false,
      "steppedLine": false,
      "targets": [
        {
          "groupBy": [
            {
              "params": [
                "$__interval"
              ],
              "type": "time"
            },
            {
              "params": [
                "null"
              ],
              "type": "fill"
            }
          ],
          "orderByTime": "ASC",
          "policy": "default",
          "query": "from(bucket:\"assetto-corsa-telemetry\")\n  |> range(start:-1m)\n  |> filter(fn:(r) =>\n    r._measurement == \"engine RPM at current time\"\n  )\n  |> aggregateWindow(every: 1s, fn: mean)",
          "refId": "A",
          "resultFormat": "time_series",
          "select": [
            [
              {
                "params": [
                  "value"
                ],
                "type": "field"
              },
              {
                "params": [],
                "type": "mean"
              }
            ]
          ],
          "tags": []
        }
      ],
      "thresholds": [
        {
          "$$hashKey": "object:228",
          "colorMode": "critical",
          "fill": true,
          "line": true,
          "op": "gt",
          "value": 8000,
          "yaxis": "left"
        },
        {
          "$$hashKey": "object:229",
          "colorMode": "ok",
          "fill": false,
          "line": false,
          "op": "lt",
          "value": 8000,
          "yaxis": "left"
        }
      ],
      "timeFrom": null,
      "timeRegions": [],
      "timeShift": null,
      "title": "RPM Dashboard",
      "tooltip": {
        "shared": true,
        "sort": 0,
        "value_type": "individual"
      },
      "type": "graph",
      "xaxis": {
        "buckets": null,
        "mode": "time",
        "name": null,
        "show": true,
        "values": []
      },
      "yaxes": [
        {
          "$$hashKey": "object:91",
          "format": "rotrpm",
          "label": null,
          "logBase": 1,
          "max": null,
          "min": null,
          "show": true
        },
        {
          "$$hashKey": "object:92",
          "format": "short",
          "label": null,
          "logBase": 1,
          "max": null,
          "min": null,
          "show": true
        }
      ],
      "yaxis": {
        "align": false,
        "alignLevel": null
      }
    },
    {
      "datasource": null,
      "fieldConfig": {
        "defaults": {
          "color": {
            "mode": "continuous-GrYlRd"
          },
          "custom": {},
          "mappings": [],
          "max": 100,
          "min": 0,
          "thresholds": {
            "mode": "absolute",
            "steps": [
              {
                "color": "green",
                "value": null
              },
              {
                "color": "red",
                "value": 80
              }
            ]
          },
          "unit": "percent"
        },
        "overrides": []
      },
      "gridPos": {
        "h": 8,
        "w": 8,
        "x": 0,
        "y": 9
      },
      "id": 8,
      "maxDataPoints": 100,
      "options": {
        "colorMode": "value",
        "graphMode": "area",
        "justifyMode": "auto",
        "orientation": "auto",
        "reduceOptions": {
          "calcs": [
            "lastNotNull"
          ],
          "fields": "",
          "values": false
        },
        "text": {},
        "textMode": "auto"
      },
      "pluginVersion": "7.4.3",
      "targets": [
        {
          "groupBy": [
            {
              "params": [
                "$__interval"
              ],
              "type": "time"
            },
            {
              "params": [
                "null"
              ],
              "type": "fill"
            }
          ],
          "orderByTime": "ASC",
          "policy": "default",
          "query": "from(bucket:\"assetto-corsa-telemetry\")\n  |> range(start:-1m)\n  |> filter(fn:(r) =>\n    r._measurement == \"brake at current time\"\n  )\n  |> aggregateWindow(every: 1s, fn: mean)",
          "refId": "A",
          "resultFormat": "time_series",
          "select": [
            [
              {
                "params": [
                  "value"
                ],
                "type": "field"
              },
              {
                "params": [],
                "type": "mean"
              }
            ]
          ],
          "tags": []
        }
      ],
      "timeFrom": null,
      "timeShift": null,
      "title": "Brake Throttle",
      "type": "stat"
    },
    {
      "datasource": null,
      "fieldConfig": {
        "defaults": {
          "color": {
            "mode": "continuous-GrYlRd"
          },
          "custom": {},
          "mappings": [],
          "max": 100,
          "min": 0,
          "thresholds": {
            "mode": "absolute",
            "steps": [
              {
                "color": "green",
                "value": null
              },
              {
                "color": "red",
                "value": 80
              }
            ]
          },
          "unit": "percent"
        },
        "overrides": []
      },
      "gridPos": {
        "h": 8,
        "w": 8,
        "x": 8,
        "y": 9
      },
      "id": 10,
      "maxDataPoints": 100,
      "options": {
        "colorMode": "value",
        "graphMode": "area",
        "justifyMode": "auto",
        "orientation": "auto",
        "reduceOptions": {
          "calcs": [
            "lastNotNull"
          ],
          "fields": "",
          "values": false
        },
        "text": {},
        "textMode": "auto"
      },
      "pluginVersion": "7.4.3",
      "targets": [
        {
          "groupBy": [
            {
              "params": [
                "$__interval"
              ],
              "type": "time"
            },
            {
              "params": [
                "null"
              ],
              "type": "fill"
            }
          ],
          "orderByTime": "ASC",
          "policy": "default",
          "query": "from(bucket:\"assetto-corsa-telemetry\")\n  |> range(start:-1m)\n  |> filter(fn:(r) =>\n    r._measurement == \"clutch at current time\"\n  )\n  |> aggregateWindow(every: 1s, fn: mean)",
          "refId": "A",
          "resultFormat": "time_series",
          "select": [
            [
              {
                "params": [
                  "value"
                ],
                "type": "field"
              },
              {
                "params": [],
                "type": "mean"
              }
            ]
          ],
          "tags": []
        }
      ],
      "timeFrom": null,
      "timeShift": null,
      "title": "Clutch Throttle",
      "type": "stat"
    },
    {
      "datasource": null,
      "fieldConfig": {
        "defaults": {
          "color": {
            "mode": "continuous-GrYlRd"
          },
          "custom": {},
          "mappings": [],
          "max": 100,
          "min": 0,
          "thresholds": {
            "mode": "absolute",
            "steps": []
          },
          "unit": "percent"
        },
        "overrides": []
      },
      "gridPos": {
        "h": 8,
        "w": 8,
        "x": 16,
        "y": 9
      },
      "id": 6,
      "maxDataPoints": 100,
      "options": {
        "colorMode": "value",
        "graphMode": "area",
        "justifyMode": "auto",
        "orientation": "auto",
        "reduceOptions": {
          "calcs": [
            "lastNotNull"
          ],
          "fields": "",
          "values": false
        },
        "text": {},
        "textMode": "auto"
      },
      "pluginVersion": "7.4.3",
      "targets": [
        {
          "groupBy": [
            {
              "params": [
                "$__interval"
              ],
              "type": "time"
            },
            {
              "params": [
                "null"
              ],
              "type": "fill"
            }
          ],
          "orderByTime": "ASC",
          "policy": "default",
          "query": "from(bucket:\"assetto-corsa-telemetry\")\n  |> range(start:-1m)\n  |> filter(fn:(r) =>\n    r._measurement == \"gas at current time\"\n  )\n  |> aggregateWindow(every: 1s, fn: mean)",
          "refId": "A",
          "resultFormat": "time_series",
          "select": [
            [
              {
                "params": [
                  "value"
                ],
                "type": "field"
              },
              {
                "params": [],
                "type": "mean"
              }
            ]
          ],
          "tags": []
        }
      ],
      "timeFrom": null,
      "timeShift": null,
      "title": "Gas Throttle",
      "type": "stat"
    },
    {
      "datasource": null,
      "description": "",
      "fieldConfig": {
        "defaults": {
          "color": {
            "mode": "continuous-GrYlRd"
          },
          "custom": {},
          "mappings": [],
          "max": 10,
          "min": 0,
          "thresholds": {
            "mode": "absolute",
            "steps": [
              {
                "color": "green",
                "value": null
              },
              {
                "color": "red",
                "value": 7
              }
            ]
          },
          "unit": "accG"
        },
        "overrides": []
      },
      "gridPos": {
        "h": 8,
        "w": 8,
        "x": 0,
        "y": 17
      },
      "id": 12,
      "maxDataPoints": 100,
      "options": {
        "colorMode": "value",
        "graphMode": "area",
        "justifyMode": "auto",
        "orientation": "auto",
        "reduceOptions": {
          "calcs": [
            "lastNotNull"
          ],
          "fields": "",
          "values": false
        },
        "text": {},
        "textMode": "auto"
      },
      "pluginVersion": "7.4.3",
      "targets": [
        {
          "groupBy": [
            {
              "params": [
                "$__interval"
              ],
              "type": "time"
            },
            {
              "params": [
                "null"
              ],
              "type": "fill"
            }
          ],
          "orderByTime": "ASC",
          "policy": "default",
          "query": "from(bucket:\"assetto-corsa-telemetry\")\n  |> range(start:-1m)\n  |> filter(fn:(r) =>\n    r._measurement == \"acceleration at current time\"\n  )\n  |> aggregateWindow(every: 1s, fn: mean)",
          "refId": "A",
          "resultFormat": "time_series",
          "select": [
            [
              {
                "params": [
                  "value"
                ],
                "type": "field"
              },
              {
                "params": [],
                "type": "mean"
              }
            ]
          ],
          "tags": []
        }
      ],
      "title": "Acceleration",
      "type": "stat"
    },
    {
      "datasource": null,
      "fieldConfig": {
        "defaults": {
          "color": {
            "mode": "thresholds"
          },
          "custom": {},
          "mappings": [],
          "thresholds": {
            "mode": "absolute",
            "steps": [
              {
                "color": "green",
                "value": null
              },
              {
                "color": "red",
                "value": 0
              }
            ]
          }
        },
        "overrides": []
      },
      "gridPos": {
        "h": 4,
        "w": 2,
        "x": 8,
        "y": 17
      },
      "id": 14,
      "maxDataPoints": 100,
      "options": {
        "colorMode": "value",
        "graphMode": "area",
        "justifyMode": "auto",
        "orientation": "auto",
        "reduceOptions": {
          "calcs": [
            "lastNotNull"
          ],
          "fields": "/^isAbsEnabled .*$/",
          "values": false
        },
        "text": {},
        "textMode": "value"
      },
      "pluginVersion": "7.4.3",
      "targets": [
        {
          "groupBy": [
            {
              "params": [
                "$__interval"
              ],
              "type": "time"
            },
            {
              "params": [
                "null"
              ],
              "type": "fill"
            }
          ],
          "orderByTime": "ASC",
          "policy": "default",
          "query": "from(bucket:\"assetto-corsa-telemetry\")\n  |> range(start:-1m)\n  |> filter(fn:(r) =>\n    r._measurement == \"isAbsEnabled\"\n  )\n  |> map(fn: (r) => ({ r with _value: if r._value == true then \"ON\" else \"OFF\"}))\n  |> last()",
          "refId": "A",
          "resultFormat": "time_series",
          "select": [
            [
              {
                "params": [
                  "value"
                ],
                "type": "field"
              },
              {
                "params": [],
                "type": "mean"
              }
            ]
          ],
          "tags": []
        }
      ],
      "timeFrom": null,
      "timeShift": null,
      "title": "ABS",
      "type": "stat"
    },
    {
      "datasource": null,
      "fieldConfig": {
        "defaults": {
          "color": {
            "mode": "thresholds"
          },
          "custom": {},
          "mappings": [],
          "thresholds": {
            "mode": "absolute",
            "steps": [
              {
                "color": "green",
                "value": null
              },
              {
                "color": "red",
                "value": 80
              }
            ]
          }
        },
        "overrides": []
      },
      "gridPos": {
        "h": 4,
        "w": 2,
        "x": 10,
        "y": 17
      },
      "id": 15,
      "maxDataPoints": 100,
      "options": {
        "colorMode": "value",
        "graphMode": "area",
        "justifyMode": "auto",
        "orientation": "auto",
        "reduceOptions": {
          "calcs": [
            "lastNotNull"
          ],
          "fields": "/^isAbsInAction .*$/",
          "values": false
        },
        "text": {},
        "textMode": "value"
      },
      "pluginVersion": "7.4.3",
      "targets": [
        {
          "groupBy": [
            {
              "params": [
                "$__interval"
              ],
              "type": "time"
            },
            {
              "params": [
                "null"
              ],
              "type": "fill"
            }
          ],
          "orderByTime": "ASC",
          "policy": "default",
          "query": "from(bucket:\"assetto-corsa-telemetry\")\n  |> range(start:-1m)\n  |> filter(fn:(r) =>\n    r._measurement == \"isAbsInAction\"\n  )\n  |> map(fn: (r) => ({ r with _value: if r._value == true then \"ON\" else \"OFF\"}))\n  |> last()",
          "refId": "A",
          "resultFormat": "time_series",
          "select": [
            [
              {
                "params": [
                  "value"
                ],
                "type": "field"
              },
              {
                "params": [],
                "type": "mean"
              }
            ]
          ],
          "tags": []
        }
      ],
      "timeFrom": null,
      "timeShift": null,
      "title": "ABS Active",
      "type": "stat"
    },
    {
      "datasource": null,
      "fieldConfig": {
        "defaults": {
          "color": {
            "mode": "thresholds"
          },
          "custom": {},
          "mappings": [],
          "thresholds": {
            "mode": "absolute",
            "steps": [
              {
                "color": "green",
                "value": null
              },
              {
                "color": "red",
                "value": 80
              }
            ]
          }
        },
        "overrides": []
      },
      "gridPos": {
        "h": 4,
        "w": 2,
        "x": 12,
        "y": 17
      },
      "id": 16,
      "maxDataPoints": 100,
      "options": {
        "colorMode": "value",
        "graphMode": "area",
        "justifyMode": "auto",
        "orientation": "auto",
        "reduceOptions": {
          "calcs": [
            "lastNotNull"
          ],
          "fields": "/^isEngineLimiterOn .*$/",
          "values": false
        },
        "text": {},
        "textMode": "value"
      },
      "pluginVersion": "7.4.3",
      "targets": [
        {
          "groupBy": [
            {
              "params": [
                "$__interval"
              ],
              "type": "time"
            },
            {
              "params": [
                "null"
              ],
              "type": "fill"
            }
          ],
          "orderByTime": "ASC",
          "policy": "default",
          "query": "from(bucket:\"assetto-corsa-telemetry\")\n  |> range(start:-1m)\n  |> filter(fn:(r) =>\n    r._measurement == \"isEngineLimiterOn\"\n  )\n  |> map(fn: (r) => ({ r with _value: if r._value == true then \"ON\" else \"OFF\"}))\n  |> last()",
          "refId": "A",
          "resultFormat": "time_series",
          "select": [
            [
              {
                "params": [
                  "value"
                ],
                "type": "field"
              },
              {
                "params": [],
                "type": "mean"
              }
            ]
          ],
          "tags": []
        }
      ],
      "timeFrom": null,
      "timeShift": null,
      "title": "Engine Limiter On",
      "type": "stat"
    },
    {
      "datasource": null,
      "fieldConfig": {
        "defaults": {
          "color": {
            "mode": "thresholds"
          },
          "custom": {},
          "mappings": [],
          "thresholds": {
            "mode": "absolute",
            "steps": [
              {
                "color": "green",
                "value": null
              },
              {
                "color": "red",
                "value": 80
              }
            ]
          }
        },
        "overrides": []
      },
      "gridPos": {
        "h": 4,
        "w": 2,
        "x": 8,
        "y": 21
      },
      "id": 17,
      "maxDataPoints": 100,
      "options": {
        "colorMode": "value",
        "graphMode": "area",
        "justifyMode": "auto",
        "orientation": "auto",
        "reduceOptions": {
          "calcs": [
            "lastNotNull"
          ],
          "fields": "/^isTcEnabled .*$/",
          "values": false
        },
        "text": {},
        "textMode": "value"
      },
      "pluginVersion": "7.4.3",
      "targets": [
        {
          "groupBy": [
            {
              "params": [
                "$__interval"
              ],
              "type": "time"
            },
            {
              "params": [
                "null"
              ],
              "type": "fill"
            }
          ],
          "orderByTime": "ASC",
          "policy": "default",
          "query": "from(bucket:\"assetto-corsa-telemetry\")\n  |> range(start:-1m)\n  |> filter(fn:(r) =>\n    r._measurement == \"isTcEnabled\"\n  )\n  |> map(fn: (r) => ({ r with _value: if r._value == true then \"ON\" else \"OFF\"}))\n  |> last()",
          "refId": "A",
          "resultFormat": "time_series",
          "select": [
            [
              {
                "params": [
                  "value"
                ],
                "type": "field"
              },
              {
                "params": [],
                "type": "mean"
              }
            ]
          ],
          "tags": []
        }
      ],
      "timeFrom": null,
      "timeShift": null,
      "title": "Traction Control",
      "type": "stat"
    },
    {
      "datasource": null,
      "fieldConfig": {
        "defaults": {
          "color": {
            "mode": "thresholds"
          },
          "custom": {},
          "mappings": [],
          "thresholds": {
            "mode": "absolute",
            "steps": [
              {
                "color": "green",
                "value": null
              },
              {
                "color": "red",
                "value": 80
              }
            ]
          }
        },
        "overrides": []
      },
      "gridPos": {
        "h": 4,
        "w": 2,
        "x": 10,
        "y": 21
      },
      "id": 18,
      "maxDataPoints": 100,
      "options": {
        "colorMode": "value",
        "graphMode": "area",
        "justifyMode": "auto",
        "orientation": "auto",
        "reduceOptions": {
          "calcs": [
            "lastNotNull"
          ],
          "fields": "/^isTcInAction .*$/",
          "values": false
        },
        "text": {},
        "textMode": "auto"
      },
      "pluginVersion": "7.4.3",
      "targets": [
        {
          "groupBy": [
            {
              "params": [
                "$__interval"
              ],
              "type": "time"
            },
            {
              "params": [
                "null"
              ],
              "type": "fill"
            }
          ],
          "orderByTime": "ASC",
          "policy": "default",
          "query": "from(bucket:\"assetto-corsa-telemetry\")\n  |> range(start:-1m)\n  |> filter(fn:(r) =>\n    r._measurement == \"isTcInAction\"\n  )\n  |> map(fn: (r) => ({ r with _value: if r._value == true then \"ON\" else \"OFF\"}))\n  |> last()",
          "refId": "A",
          "resultFormat": "time_series",
          "select": [
            [
              {
                "params": [
                  "value"
                ],
                "type": "field"
              },
              {
                "params": [],
                "type": "mean"
              }
            ]
          ],
          "tags": []
        }
      ],
      "timeFrom": null,
      "timeShift": null,
      "title": "Traction Control Active",
      "type": "stat"
    },
    {
      "datasource": null,
      "fieldConfig": {
        "defaults": {
          "color": {
            "mode": "thresholds"
          },
          "custom": {},
          "mappings": [],
          "thresholds": {
            "mode": "absolute",
            "steps": [
              {
                "color": "green",
                "value": null
              },
              {
                "color": "red",
                "value": 80
              }
            ]
          }
        },
        "overrides": []
      },
      "gridPos": {
        "h": 4,
        "w": 2,
        "x": 12,
        "y": 21
      },
      "id": 19,
      "interval": null,
      "maxDataPoints": 100,
      "options": {
        "colorMode": "value",
        "graphMode": "area",
        "justifyMode": "auto",
        "orientation": "auto",
        "reduceOptions": {
          "calcs": [
            "lastNotNull"
          ],
          "fields": "/^isInPit .*$/",
          "values": false
        },
        "text": {},
        "textMode": "value"
      },
      "pluginVersion": "7.4.3",
      "targets": [
        {
          "groupBy": [
            {
              "params": [
                "$__interval"
              ],
              "type": "time"
            },
            {
              "params": [
                "null"
              ],
              "type": "fill"
            }
          ],
          "orderByTime": "ASC",
          "policy": "default",
          "query": "from(bucket:\"assetto-corsa-telemetry\")\n  |> range(start:-1m)\n  |> filter(fn:(r) =>\n    r._measurement == \"isInPit\"\n  )\n  |> map(fn: (r) => ({ r with _value: if r._value == true then \"ON\" else \"OFF\"}))\n  |> last()",
          "refId": "A",
          "resultFormat": "time_series",
          "select": [
            [
              {
                "params": [
                  "value"
                ],
                "type": "field"
              },
              {
                "params": [],
                "type": "mean"
              }
            ]
          ],
          "tags": []
        }
      ],
      "timeFrom": null,
      "timeShift": null,
      "title": "In Pit",
      "type": "stat"
    }
  ],
  "refresh": "5s",
  "schemaVersion": 27,
  "style": "dark",
  "tags": [],
  "templating": {
    "list": []
  },
  "time": {
    "from": "now-1m",
    "to": "now"
  },
  "timepicker": {
    "hidden": false,
    "refresh_intervals": [
      "5s",
      "10s",
      "30s",
      "1m",
      "5m",
      "15m",
      "30m",
      "1h",
      "2h",
      "1d"
    ]
  },
  "timezone": "",
  "title": "Telemetry Dashboard",
  "uid": "dLBRwTyMz",
  "version": 15
}